string_pi/__init__.py
string_pi/core.py
string_pi-0.1.0.dist-info/licenses/LICENSE
string_pi-0.1.0.dist-info/METADATA
string_pi-0.1.0.dist-info/WHEEL
string_pi-0.1.0.dist-info/top_level.txt
string_pi-0.1.0.dist-info/RECORD
