Metadata-Version: 2.4
Name: string-pi
Version: 0.1.0
Summary: Implementation of the Saha-Sinha Pi formula derived from string theory
Author-email: Vecture Laboratories <info@vecture.de>
Project-URL: Homepage, https://github.com/VectureLaboratories/string-pi
Project-URL: Bug Tracker, https://github.com/VectureLaboratories/string-pi/issues
Classifier: Programming Language :: Python :: 3
Classifier: License :: Other/Proprietary License
Classifier: Operating System :: OS Independent
Requires-Python: >=3.9
License-File: LICENSE
Requires-Dist: mpmath
Dynamic: license-file
